<?xml version="1.0" encoding="utf-8"?>
<LanguageData>
  <!--The following translations were generated by https://www.deepl.com/-->
  <!-- EN: Christmas reindeer -->
  <CSChristmasReindeer.label>Renne de Noël</CSChristmasReindeer.label>
  <!-- EN: Christmas reindeer are medium-sized herding herbivores. They normally pull santa claus's sleigh with. You can milk them for chistmas spirit. -->
  <CSChristmasReindeer.description>Les rennes de Noël sont des herbivores de taille moyenne. Ils tirent normalement le traîneau du Père Noël avec. Vous pouvez les traire pour obtenir l'esprit de Noël.</CSChristmasReindeer.description>
  <!-- EN: left hoof -->
  <CSChristmasReindeer.tools.left_hoof.label>sabot gauche</CSChristmasReindeer.tools.left_hoof.label>
  <!-- EN: right hoof -->
  <CSChristmasReindeer.tools.right_hoof.label>sabot droit</CSChristmasReindeer.tools.right_hoof.label>
  <!-- EN: head -->
  <CSChristmasReindeer.tools.head.label>tête</CSChristmasReindeer.tools.head.label>
</LanguageData>
