<?xml version="1.0" encoding="utf-8"?>
<LanguageData>
  <!--The following translations were generated by https://www.deepl.com/-->
  <!-- EN: Cinnamon tree -->
  <CSCinnamonTree.label>Zimtbaum</CSCinnamonTree.label>
  <!-- EN: A tree producing cinnamon. -->
  <CSCinnamonTree.description>Ein Baum, der Zimt produziert.</CSCinnamonTree.description>
  <!-- EN: Glühwein -->
  <CSGluehwein.label>Glühwein</CSGluehwein.label>
  <!-- EN: It is a traditional beverage offered during the Christmas holidays. -->
  <CSGluehwein.description>Es ist ein traditionelles Getränk während der Weihnachtsfeiertage angeboten.</CSGluehwein.description>
  <!-- EN: Drink {0} -->
  <CSGluehwein.ingestible.ingestCommandString>Getränk {0}</CSGluehwein.ingestible.ingestCommandString>
  <!-- EN: Drinking {0}. -->
  <CSGluehwein.ingestible.ingestReportString>Trinken {0}.</CSGluehwein.ingestible.ingestReportString>
  <!-- EN: Grapevine -->
  <CSGrapevinePlant.label>Weinrebe</CSGrapevinePlant.label>
  <!-- EN: A plant producing grapes for wine brewing. -->
  <CSGrapevinePlant.description>Eine Pflanze, die Trauben für das Weinbrauen produziert.</CSGrapevinePlant.description>
  <!-- EN: Illicium verum -->
  <CSIlliciumVerumPlant.label>Illicium verum</CSIlliciumVerumPlant.label>
  <!-- EN: A plant producing star anise. -->
  <CSIlliciumVerumPlant.description>Eine Pflanze, die Sternanis produziert.</CSIlliciumVerumPlant.description>
  <!-- EN: Must -->
  <CSMust.label>Muss</CSMust.label>
  <!-- EN: Un-fermented wine. This substance needs to ferment in a wine barrel before it becomes drinkable wine. -->
  <CSMust.description>Ungegorener Wein. Diese Substanz muss in einem Weinfass gären, bevor sie zu trinkbarem Wein wird.</CSMust.description>
  <!-- EN: Cinnamon -->
  <CSRawCinnamon.label>Zimt</CSRawCinnamon.label>
  <!-- EN: A nice smelling thing. -->
  <CSRawCinnamon.description>Ein schön riechendes Ding.</CSRawCinnamon.description>
  <!-- EN: Grapes -->
  <CSRawGrapes.label>Weintrauben</CSRawGrapes.label>
  <!-- EN: Grapes for eating and wine brewing. -->
  <CSRawGrapes.description>Trauben zum Essen und Weinbrauen.</CSRawGrapes.description>
  <!-- EN: Star anise -->
  <CSRawStarAnise.label>Sternanis</CSRawStarAnise.label>
  <CSRawStarAnise.description>Ein schön riechendes Ding.</CSRawStarAnise.description>
  <!-- EN: Sugar beet -->
  <CSRawSugarBeet.label>Zuckerrübe</CSRawSugarBeet.label>
  <!-- EN: Sugar beet used for sugar making. -->
  <CSRawSugarBeet.description>Zuckerrüben für die Zuckerherstellung verwendet.</CSRawSugarBeet.description>
  <!-- EN: Sugar -->
  <CSSugar.label>Zucker</CSSugar.label>
  <!-- EN: A sweet thing. Don't eat to much of it. -->
  <CSSugar.description>Eine süße Sache. Essen Sie nicht zu viel davon.</CSSugar.description>
  <CSSugarBeet.label>Zuckerrübe</CSSugarBeet.label>
  <!-- EN: A plant producing sugar beet for making sugar. -->
  <CSSugarBeet.description>Eine Pflanze, die Zuckerrüben für die Herstellung von Zucker produziert.</CSSugarBeet.description>
  <!-- EN: Wine -->
  <CSWine.label>Wein</CSWine.label>
  <!-- EN: A noble alcohol. Excessive consumption can lead to alcohol blackouts and, over time, addiction. -->
  <CSWine.description>Ein edler Alkohol. Übermäßiger Konsum kann zu Alkohol-Blackouts und mit der Zeit zur Abhängigkeit führen.</CSWine.description>
  <CSWine.ingestible.ingestCommandString>Getränk {0}</CSWine.ingestible.ingestCommandString>
  <CSWine.ingestible.ingestReportString>Trinken {0}.</CSWine.ingestible.ingestReportString>
  <!-- EN: bottle -->
  <CSWine.tools.bottle.label>Flasche</CSWine.tools.bottle.label>
  <!-- EN: neck -->
  <CSWine.tools.neck.label>Hals</CSWine.tools.neck.label>
  <!-- EN: Wine Barrel -->
  <CSWineBarrel.label>Weinfass</CSWineBarrel.label>
  <!-- EN: For fermenting wine. -->
  <CSWineBarrel.description>Für gärenden Wein.</CSWineBarrel.description>
</LanguageData>
